openrouter/__init__.py
openrouter/llms.py
openrouter/message.py
openrouter/openrouter.py
openrouter/openrouter_provider.py
openrouter/tool.py
openrouter_provider-1.0.11.dist-info/METADATA
openrouter_provider-1.0.11.dist-info/WHEEL
openrouter_provider-1.0.11.dist-info/top_level.txt
openrouter_provider-1.0.11.dist-info/RECORD
