Metadata-Version: 2.4
Name: openrouter-provider
Version: 1.0.11
Summary: This is an unofficial wrapper of OpenRouter.
Author-email: Keisuke Miyamto <aichiboyhighschool@gmail.com>
Requires-Python: >=3.7
Requires-Dist: annotated-types
Requires-Dist: anyio
Requires-Dist: build
Requires-Dist: certifi
Requires-Dist: charset-normalizer
Requires-Dist: distro
Requires-Dist: docutils
Requires-Dist: h11
Requires-Dist: httpcore
Requires-Dist: httpx
Requires-Dist: id
Requires-Dist: idna
Requires-Dist: jaraco.classes
Requires-Dist: jaraco.context
Requires-Dist: jaraco.functools
Requires-Dist: jiter
Requires-Dist: keyring
Requires-Dist: markdown-it-py
Requires-Dist: mdurl
Requires-Dist: more-itertools
Requires-Dist: nh3
Requires-Dist: openai
Requires-Dist: packaging
Requires-Dist: pillow
Requires-Dist: pydantic
Requires-Dist: pydantic_core
Requires-Dist: Pygments
Requires-Dist: pyproject_hooks
Requires-Dist: python-dotenv
Requires-Dist: readme_renderer
Requires-Dist: requests
Requires-Dist: requests-toolbelt
Requires-Dist: rfc3986
Requires-Dist: rich
Requires-Dist: sniffio
Requires-Dist: tqdm
Requires-Dist: twine
Requires-Dist: typing-inspection
Requires-Dist: typing_extensions
Requires-Dist: urllib3
